[
    {
        "id":  "mg_gen_036",
        "subject":  "mg",
        "category":  "民法",
        "subcategory":  "合同",
        "type":  "single",
        "stem":  "甲与乙签订房屋买卖合同后，房价大涨。甲以情势变更为由请求法院变更合同价格。法院应审查的要件不包括：",
        "options":  [
                        "A. 合同成立后客观情况发生重大变化",
                        "B. 该变化是当事人订立合同时无法预见的",
                        "C. 继续履行对一方明显不公平",
                        "D. 甲在签约时存在重大误解"
                    ],
        "answer":  "D",
        "analysis":  "根据《民法典》第533条，情势变更的构成要件为：(1)合同成立后客观情况发生了当事人在订立合同时无法预见的重大变化（A+B）；(2)不属于商业风险；(3)继续履行合同对当事人一方明显不公平（C）。D重大误解属于可撤销事由（第147条），不属于情势变更的审查要件。两者是不同的制度。",
        "rule":  "情势变更三要件：不可预见的重大变化+非商业风险+继续履行明显不公平",
        "lawRef":  "《民法典》第533条",
        "trap":  "D是干扰项，重大误解是独立的可撤销事由",
        "difficulty":  3,
        "tags":  [
                     "情势变更",
                     "合同变更",
                     "商业风险"
                 ]
    },
    {
        "id":  "mg_gen_037",
        "subject":  "mg",
        "category":  "民法",
        "subcategory":  "合同",
        "type":  "single",
        "stem":  "甲（出卖人）与乙（买受人）签订买卖合同，约定甲于6月1日交付货物。5月20日甲明确表示将不会履行合同。乙：",
        "options":  [
                        "A. 只能等到6月1日届满后才能主张违约",
                        "B. 可以立即解除合同并请求损害赔偿",
                        "C. 只能请求甲继续履行",
                        "D. 必须等甲实际违约后才能采取措施"
                    ],
        "answer":  "B",
        "analysis":  "根据《民法典》第578条（预期违约/先期违约），当事人一方明确表示或者以自己的行为表明不履行合同义务的，对方可以在履行期限届满前请求其承担违约责任。甲在履行期届满前明确表示不履行，构成明示预期违约，乙无需等到6月1日，可以立即解除合同并主张损害赔偿。",
        "rule":  "预期违约：明确表示不履行的，对方可在履行期前主张违约责任",
        "lawRef":  "《民法典》第578条",
        "trap":  "易误选A，忽略预期违约制度赋予守约方的提前救济权",
        "difficulty":  3,
        "tags":  [
                     "预期违约",
                     "解除合同",
                     "违约责任"
                 ]
    },
    {
        "id":  "mg_gen_038",
        "subject":  "mg",
        "category":  "民法",
        "subcategory":  "合同",
        "type":  "single",
        "stem":  "甲将A物出卖给乙，同时将A物出卖给丙。乙先付款但未交付，丙后付款且已交付。A物所有权归：",
        "options":  [
                        "A. 乙，因为先付款",
                        "B. 丙，因为已交付",
                        "C. 甲，因为一物二卖无效",
                        "D. 乙和丙共有"
                    ],
        "answer":  "B",
        "analysis":  "根据《民法典》第224条，动产物权的设立和转让，自交付时发生效力。动产所有权以交付为转移要件，不以付款时间为准。甲将A物交付给丙，丙取得所有权。乙虽先付款但未获交付，只能向甲主张违约损害赔偿。一物二卖中两个买卖合同均有效（合同效力独立于物权变动）。",
        "rule":  "动产物权变动以交付为准，先付款不等于取得所有权",
        "lawRef":  "《民法典》第224条",
        "trap":  "易误选A，混淆债权关系（合同）与物权变动（交付）",
        "difficulty":  3,
        "tags":  [
                     "动产交付",
                     "一物二卖",
                     "物权变动"
                 ]
    },
    {
        "id":  "mg_gen_039",
        "subject":  "mg",
        "category":  "民法",
        "subcategory":  "物权",
        "type":  "single",
        "stem":  "甲的房屋与乙的房屋相邻，甲在自己土地上建造围墙导致乙房屋采光严重受阻。乙可以主张：",
        "options":  [
                        "A. 基于相邻关系请求甲排除妨碍",
                        "B. 无权干涉，甲在自己土地上建设",
                        "C. 请求行政机关拆除",
                        "D. 只能请求损害赔偿"
                    ],
        "answer":  "A",
        "analysis":  "根据《民法典》第288、293条，不动产权利人对相邻权利人因通行、排水、通风、采光等需要应提供必要便利（相邻关系）。第293条规定建造建筑物不得违反国家有关工程建设标准，不得妨碍相邻建筑物的通风、采光和日照。甲建围墙严重妨碍乙采光，乙可基于相邻关系请求排除妨碍。",
        "rule":  "相邻关系：不得妨碍相邻不动产的通风采光日照",
        "lawRef":  "《民法典》第288条、第293条",
        "trap":  "易误选B，所有权行使受相邻关系限制",
        "difficulty":  2,
        "tags":  [
                     "相邻关系",
                     "采光权",
                     "排除妨碍"
                 ]
    },
    {
        "id":  "mg_gen_040",
        "subject":  "mg",
        "category":  "民法",
        "subcategory":  "人格权",
        "type":  "single",
        "stem":  "某医院未经患者甲同意，将甲的病历资料用于学术论文发表（含甲的姓名和详细病情）。甲可以主张侵犯：",
        "options":  [
                        "A. 名誉权",
                        "B. 隐私权",
                        "C. 健康权",
                        "D. 财产权"
                    ],
        "answer":  "B",
        "analysis":  "根据《民法典》第1032条，自然人享有隐私权，任何组织或个人不得以刺探、侵扰、泄露、公开等方式侵害他人的隐私权。第1034条规定个人信息中的私密信息适用隐私权保护规定。患者的病历资料包含健康状况等私密信息，属于隐私范畴。医院未经同意公开发表构成对甲隐私权的侵害。",
        "rule":  "病历资料属于私密信息，未经同意公开侵犯隐私权",
        "lawRef":  "《民法典》第1032条、第1226条",
        "trap":  "易误选A，公开病情不等于贬低评价（名誉权需降低社会评价）",
        "difficulty":  3,
        "tags":  [
                     "隐私权",
                     "个人信息",
                     "医疗隐私",
                     "病历"
                 ]
    },
    {
        "id":  "mg_gen_041",
        "subject":  "mg",
        "category":  "民法",
        "subcategory":  "合同",
        "type":  "multiple",
        "stem":  "关于不安抗辩权，下列说法正确的有：",
        "options":  [
                        "A. 应当先履行债务的当事人有确切证据证明对方有丧失商业信誉情形的可以中止履行",
                        "B. 应当先履行债务的当事人有确切证据证明对方转移财产逃避债务的可以中止履行",
                        "C. 中止履行后应当及时通知对方",
                        "D. 对方在合理期限内未恢复履行能力且未提供担保的，中止方可以解除合同"
                    ],
        "answer":  [
                       "A",
                       "B",
                       "C",
                       "D"
                   ],
        "analysis":  "根据《民法典》第527-528条：先履行方在有确切证据证明对方有经营严重恶化（含丧失商业信誉A）、转移财产抽逃资金以逃避债务（B）、丧失商业信誉、有丧失或可能丧失履行能力的其他情形时，可中止履行。C正确，中止后应及时通知对方（第527条）。D正确，第528条对方在合理期限内未恢复履行能力且未提供适当担保的，中止方可以解除合同。",
        "rule":  "不安抗辩权：先履行方+确切证据+中止+通知+合理期限后可解除",
        "lawRef":  "《民法典》第527-528条",
        "trap":  "全选题，考查不安抗辩权的完整行使流程",
        "difficulty":  3,
        "tags":  [
                     "不安抗辩权",
                     "中止履行",
                     "合同解除"
                 ]
    },
    {
        "id":  "mg_gen_042",
        "subject":  "mg",
        "category":  "民法",
        "subcategory":  "侵权",
        "type":  "multiple",
        "stem":  "关于医疗损害责任，下列说法正确的有：",
        "options":  [
                        "A. 患者在诊疗活动中受到损害，医疗机构有过错的承担赔偿责任",
                        "B. 医疗机构违反告知义务造成损害的应承担赔偿责任",
                        "C. 紧急情况下不能取得患者意见的经批准可以立即实施相应医疗措施",
                        "D. 患者因药品缺陷受到损害可以向生产者或医疗机构请求赔偿"
                    ],
        "answer":  [
                       "A",
                       "B",
                       "C",
                       "D"
                   ],
        "analysis":  "根据《民法典》第1218-1224条：A正确，第1218条医疗损害适用过错责任。B正确，第1219条医疗机构的告知义务，未尽到告知义务造成损害应赔偿。C正确，第1220条紧急情况不能取得患者或近亲属意见时，经医疗机构负责人批准可实施。D正确，第1223条因药品缺陷造成损害可向药品生产者或医疗机构请求赔偿。",
        "rule":  "医疗损害：过错责任+告知义务+紧急救治+药品缺陷（选择请求权）",
        "lawRef":  "《民法典》第1218-1224条",
        "trap":  "全选题，考查医疗损害责任的完整框架",
        "difficulty":  3,
        "tags":  [
                     "医疗损害",
                     "过错责任",
                     "告知义务",
                     "药品缺陷"
                 ]
    },
    {
        "id":  "mg_gen_043",
        "subject":  "mg",
        "category":  "民法",
        "subcategory":  "物权",
        "type":  "multiple",
        "stem":  "关于居住权，下列说法正确的有：",
        "options":  [
                        "A. 居住权是《民法典》新设立的用益物权",
                        "B. 居住权人有权按照合同约定对他人的住宅享有占有使用的权利",
                        "C. 居住权自登记时设立",
                        "D. 居住权不得转让和继承"
                    ],
        "answer":  [
                       "A",
                       "B",
                       "C",
                       "D"
                   ],
        "analysis":  "根据《民法典》第366-371条（民法典新增）：A正确，居住权是民法典新设的用益物权类型。B正确，第366条居住权人有权按合同约定占有使用他人住宅以满足生活居住需要。C正确，第368条居住权自登记时设立。D正确，第369条居住权不得转让、继承。设立居住权的住宅不得出租（但当事人另有约定的除外）。",
        "rule":  "居住权：民法典新设+用益物权+登记设立+不得转让继承",
        "lawRef":  "《民法典》第366-371条",
        "trap":  "这是民法典全新制度，是法考必考点",
        "difficulty":  3,
        "tags":  [
                     "居住权",
                     "用益物权",
                     "民法典新增",
                     "登记设立"
                 ]
    },
    {
        "id":  "mg_gen_044",
        "subject":  "mg",
        "category":  "民法",
        "subcategory":  "合同",
        "type":  "multiple",
        "stem":  "关于合同解除的法律效果，下列说法正确的有：",
        "options":  [
                        "A. 尚未履行的终止履行",
                        "B. 已经履行的可以请求恢复原状",
                        "C. 合同解除不影响违约责任的承担",
                        "D. 当事人可以请求损害赔偿"
                    ],
        "answer":  [
                       "A",
                       "B",
                       "C",
                       "D"
                   ],
        "analysis":  "根据《民法典》第566条：合同解除后，尚未履行的终止履行（A✓）；已经履行的，根据履行情况和合同性质，当事人可以请求恢复原状或者采取其他补救措施（B✓）；合同解除不影响合同中结算和清理条款的效力（含违约条款C✓）；第566条第2款，合同因违约解除的，解除权人可以请求违约方承担违约责任，但当事人另有约定的除外（含损害赔偿D✓）。",
        "rule":  "合同解除效果：终止+恢复原状+不影响违约责任+损害赔偿",
        "lawRef":  "《民法典》第566条",
        "trap":  "全选题，C项是重要考点：解除不消灭违约责任",
        "difficulty":  3,
        "tags":  [
                     "合同解除",
                     "恢复原状",
                     "违约责任",
                     "损害赔偿"
                 ]
    },
    {
        "id":  "mg_gen_045",
        "subject":  "mg",
        "category":  "民法",
        "subcategory":  "担保",
        "type":  "multiple",
        "stem":  "关于保证合同，下列说法正确的有：",
        "options":  [
                        "A. 保证方式分为一般保证和连带责任保证",
                        "B. 当事人未约定保证方式的推定为一般保证",
                        "C. 一般保证的保证人享有先诉抗辩权",
                        "D. 保证期间未约定的为主债务履行期限届满之日起6个月"
                    ],
        "answer":  [
                       "A",
                       "B",
                       "C",
                       "D"
                   ],
        "analysis":  "根据《民法典》第686-694条：A正确，第686条保证分一般保证和连带保证。B正确，第686条第2款当事人在保证合同中未约定或约定不明的视为一般保证（重大修改！旧担保法推定为连带保证）。C正确，第687条一般保证人享有先诉抗辩权（先执行债务人财产再找保证人）。D正确，第692条未约定保证期间的为6个月。",
        "rule":  "民法典保证重大修改：未约定保证方式→推定为一般保证（旧法为连带）",
        "lawRef":  "《民法典》第686-694条",
        "trap":  "B项是民法典重大修改：旧法推定连带，新法推定一般保证",
        "difficulty":  4,
        "tags":  [
                     "保证合同",
                     "一般保证",
                     "连带保证",
                     "先诉抗辩权"
                 ]
    }
]
