[
    {
        "id":  "xf_gen_006",
        "subject":  "xf",
        "category":  "宪法",
        "subcategory":  "国家机构",
        "type":  "single",
        "stem":  "根据我国宪法，国家主席的任期与下列哪个机关每届任期相同：",
        "options":  [
                        "A. 全国人民代表大会",
                        "B. 国务院",
                        "C. 最高人民法院",
                        "D. 以上都是"
                    ],
        "answer":  "D",
        "analysis":  "根据《宪法》第60条、第79条、第87条、第124条，全国人大每届任期5年，国家主席任期与全国人大每届任期相同（5年）。国务院总理、最高法院长、最高检检察长任期也与全国人大相同。2018年宪法修正案取消了国家主席连续任职不得超过两届的限制，但任期仍为5年一届。",
        "rule":  "国家机构任期统一：均与全国人大每届任期相同（5年）",
        "lawRef":  "《宪法》第60条、第66条、第79条",
        "trap":  "易误选A，实际上所有中央国家机关领导人任期均与全国人大同步",
        "difficulty":  2,
        "tags":  [
                     "国家主席",
                     "任期",
                     "5年",
                     "全国人大"
                 ]
    },
    {
        "id":  "xf_gen_007",
        "subject":  "xf",
        "category":  "宪法",
        "subcategory":  "国家机构",
        "type":  "single",
        "stem":  "根据我国宪法，下列哪个机关有权决定省、自治区、直辖市的设立、撤销和更名：",
        "options":  [
                        "A. 全国人民代表大会",
                        "B. 国务院",
                        "C. 全国人大常委会",
                        "D. 中央军事委员会"
                    ],
        "answer":  "A",
        "analysis":  "根据《宪法》第62条第13项，全国人民代表大会有权批准省、自治区和直辖市的建置（设立、撤销、更名等）。注意：国务院（B）有权批准省以下的行政区划划分（如市、县的设立变更）。省级行政区划变动涉及国家结构的重大事项，须由最高国家权力机关决定。",
        "rule":  "省级行政区划变动→全国人大；省以下→国务院",
        "lawRef":  "《宪法》第62条第13项、第89条第15项",
        "trap":  "易误选B，混淆省级建置（全国人大）与省以下区划（国务院）",
        "difficulty":  3,
        "tags":  [
                     "行政区划",
                     "全国人大",
                     "省级建置"
                 ]
    },
    {
        "id":  "xf_gen_008",
        "subject":  "xf",
        "category":  "宪法",
        "subcategory":  "立法",
        "type":  "multiple",
        "stem":  "关于我国的立法体制，下列说法正确的有：",
        "options":  [
                        "A. 全国人大制定和修改刑事、民事等基本法律",
                        "B. 全国人大常委会制定和修改基本法律以外的法律",
                        "C. 国务院制定行政法规",
                        "D. 省级人大及其常委会制定地方性法规"
                    ],
        "answer":  [
                       "A",
                       "B",
                       "C",
                       "D"
                   ],
        "analysis":  "根据《宪法》和《立法法》：A正确，第62条全国人大制定修改刑事、民事、国家机构和其他基本法律。B正确，第67条常委会制定修改基本法律以外的法律。C正确，第89条国务院根据宪法和法律制定行政法规。D正确，第100条省级人大及其常委会可制定地方性法规（不同宪法法律抵触）。设区的市也可就城建环保等事项制定地方性法规。",
        "rule":  "多层级立法体制：全国人大（基本法律）+常委会（一般法律）+国务院（行政法规）+地方（地方性法规）",
        "lawRef":  "《宪法》第62、67、89、100条",
        "trap":  "全选题，考查我国多层级统一立法体制",
        "difficulty":  1,
        "tags":  [
                     "立法体制",
                     "基本法律",
                     "行政法规",
                     "地方性法规"
                 ]
    }
]
